address/__init__.py
address/admin.py
address/apps.py
address/compat.py
address/forms.py
address/models.py
address/utils.py
address/widgets.py
address/migrations/0001_initial.py
address/migrations/0002_auto_20160213_1726.py
address/migrations/0003_auto_20200830_1851.py
address/migrations/0004_auto_20210618_2016.py
address/migrations/__init__.py
address/static/address/css/address.css
address/static/address/js/address.js
django_arcgis_address-1.2.6.dist-info/LICENSE
django_arcgis_address-1.2.6.dist-info/METADATA
django_arcgis_address-1.2.6.dist-info/WHEEL
django_arcgis_address-1.2.6.dist-info/top_level.txt
django_arcgis_address-1.2.6.dist-info/RECORD
